simplekit/__init__.py
simplekit/file_utils.py
simplekit/string_utils.py
simplekit/text_tools.py
simplekit/ts.py
mrlee-0.1.0.dist-info/LICENSE
mrlee-0.1.0.dist-info/METADATA
mrlee-0.1.0.dist-info/WHEEL
mrlee-0.1.0.dist-info/top_level.txt
mrlee-0.1.0.dist-info/RECORD
