Metadata-Version: 2.2
Name: mrlee
Version: 0.1.0
Summary: A collection of simple and useful utilities for file and string operations.
Home-page: https://github.com/kevinlulee/mrlee
Author: Kevin Lee
Author-email: kevinlulee1@gmail.com
Classifier: Programming Language :: Python :: 3
Classifier: License :: OSI Approved :: MIT License
Classifier: Operating System :: OS Independent
Requires-Python: >=3.7
License-File: LICENSE
Provides-Extra: dev
Requires-Dist: pytest>=6.0; extra == "dev"
Dynamic: author
Dynamic: author-email
Dynamic: classifier
Dynamic: description
Dynamic: description-content-type
Dynamic: home-page
Dynamic: provides-extra
Dynamic: requires-python
Dynamic: summary
